pandas_numpy_lib/__init__.py
pandas_numpy_lib/core.py
pandas_numpy_lib-0.1.dist-info/LICENSE
pandas_numpy_lib-0.1.dist-info/METADATA
pandas_numpy_lib-0.1.dist-info/WHEEL
pandas_numpy_lib-0.1.dist-info/top_level.txt
pandas_numpy_lib-0.1.dist-info/RECORD
